{
  "defaultSeverity": "warning",
  "extends": [
    "tslint:recommended"
  ],
  "linterOptions": {
    "exclude": [
      "node_modules/**"
    ]
  },
  "rules": {
    "indent": [true, "spaces", 2],
    "interface-name": false,
    "no-consecutive-blank-lines": false,
    "object-literal-sort-keys": false,
    "ordered-imports": false,
    "quotemark": [true, "single"],
    "variable-name": false,
    "max-line-length": false,
    "max-classes-per-file": false,
    "triple-equals": false,
    "one-variable-per-declaration": false,
    "no-console": false,
    "no-namespace": false,
    "no-bitwise": false,
    "no-shadowed-variable": false,
    "radix": false,
    "prefer-const": false,
    "no-empty": false,
    "class-name": false,
    "jsdoc-format": false,
    "no-reference": false,
    "no-conditional-assignment": false,
    "prefer-for-of": false,
    "unified-signatures": false
  }
}
